spor/__init__.py
spor/alignment/__init__.py
spor/alignment/matrix.py
spor/alignment/smith_waterman.py
spor/anchor.py
spor/cli.py
spor/diff.py
spor/repository/__init__.py
spor/repository/persistence.py
spor/repository/repository.py
spor/updating.py
spor/version.py
spor-1.1.6.dist-info/entry_points.txt
spor-1.1.6.dist-info/LICENSE
spor-1.1.6.dist-info/WHEEL
spor-1.1.6.dist-info/METADATA
spor-1.1.6.dist-info/RECORD
