Metadata-Version: 2.1
Name: spor
Version: 1.1.6
Summary: A system for anchoring metadata in external files to source code
Home-page: https://github.com/abingham/spor
License: MIT
Author: Austin Bingham
Author-email: austin@sixty-north.com
Requires-Python: >=3.4
Classifier: License :: OSI Approved :: MIT License
Classifier: Programming Language :: Python :: 3
Classifier: Programming Language :: Python :: 3.4
Classifier: Programming Language :: Python :: 3.5
Classifier: Programming Language :: Python :: 3.6
Classifier: Programming Language :: Python :: 3.7
Classifier: Programming Language :: Python :: 3.8
Requires-Dist: docopt_subcommands (>=2.3,<3.0)
Requires-Dist: exit_codes (>=1.1,<2.0)
Requires-Dist: pyyaml (>=3.13,<4.0)
Project-URL: Repository, https://github.com/abingham/spor
